MANIFEST.in
README.md
setup.py
NP6HelperHttp/__init__.py
NP6HelperHttp/helperHttp.py
NP6HelperHttp.egg-info/PKG-INFO
NP6HelperHttp.egg-info/SOURCES.txt
NP6HelperHttp.egg-info/dependency_links.txt
NP6HelperHttp.egg-info/not-zip-safe
NP6HelperHttp.egg-info/top_level.txt