Metadata-Version: 1.0
Name: NP6HelperHttp
Version: 0.1
Summary: helper to analyze header Http
Home-page: https://github.com/NP6/Python
Author: NP6 -SpaghetTeam
Author-email: fpi@np6.com
License: CC Licence
Keywords: http header content-type NP6
Platform: UNKNOWN
